pfun/__init__.py
pfun/aio_trampoline.py
pfun/clock.py
pfun/console.py
pfun/dict.py
pfun/effect.c
pfun/effect.pyi
pfun/effect.pyx
pfun/either.py
pfun/files.py
pfun/functions.py
pfun/functor.py
pfun/http.py
pfun/hypothesis_strategies.py
pfun/immutable.py
pfun/lens.py
pfun/list.py
pfun/logging.py
pfun/maybe.py
pfun/monad.py
pfun/mypy_plugin.py
pfun/operator.py
pfun/protocols.py
pfun/py.typed
pfun/random.py
pfun/schedule.py
pfun/sql.py
pfun/state.py
pfun/subprocess.py
pfun/trampoline.py
pfun/effect.cpython-39-darwin.so
pfun-0.13.2.dist-info/LICENSE
pfun-0.13.2.dist-info/METADATA
pfun-0.13.2.dist-info/WHEEL
pfun-0.13.2.dist-info/RECORD
