Metadata-Version: 2.1
Name: pfun
Version: 0.13.2
Summary: Functional, composable, asynchronous, type-safe Python.
Author: Sune Debel
Requires-Python: >=3.7,<3.12
Classifier: Programming Language :: Python :: 3
Classifier: Programming Language :: Python :: 3.7
Classifier: Programming Language :: Python :: 3.8
Classifier: Programming Language :: Python :: 3.9
Classifier: Programming Language :: Python :: 3.10
Classifier: Programming Language :: Python :: 3.11
Provides-Extra: http
Provides-Extra: sql
Provides-Extra: test
Requires-Dist: aiohttp[speedups] (>=3.7.4,<4.0.0) ; extra == "http"
Requires-Dist: asyncpg (>=0.28.0,<0.29.0) ; extra == "sql"
Requires-Dist: dill (>=0.3.2,<0.4.0)
Requires-Dist: hypothesis (>=6.8.5,<7.0.0) ; extra == "test"
Requires-Dist: typing-extensions (>=3.10.0.0,<4.0.0.0) ; python_version >= "3.7" and python_version < "3.11"
Requires-Dist: typing-extensions (>=4.8.0,<5.0.0) ; python_version == "3.11"
